MathDict/__init__.py
MathDict-0.1.3.dist-info/DESCRIPTION.rst
MathDict-0.1.3.dist-info/METADATA
MathDict-0.1.3.dist-info/metadata.json
MathDict-0.1.3.dist-info/RECORD
MathDict-0.1.3.dist-info/top_level.txt
MathDict-0.1.3.dist-info/WHEEL
