Metadata-Version: 2.0
Name: MathDict
Version: 0.1.3
Summary: Python dict / collections Mapping sub-class that can work with mathematical operators
Home-page: https://github.com/MBALearnsToCode/PyMathDict
Author: Vinh Luong (a.k.a. MBALearnsToCode)
Author-email: MBALearnsToCode@UChicago.edu
License: MIT License
Keywords: math dict
Platform: UNKNOWN
Requires-Dist: FrozenDict
Requires-Dist: Helpy
